Workbook

Sheet DATA DE CONTROLES Y LLAVES
Q1: a la venta
G2: CENSO | K2: bloqueado disleidy diaz | L2: 84B | Q2: 221B | R2: 222B
G3: BLOQUES 27 AL 32
O4: Alejandro Tecnico | P4: 1B
B5: BLOQ. | C5: ESC. | D5: PISOS | E5: APTO. | F5: NOMBRES | G5: APELLIDOS | H5: ESTADO DE CONTROLES | I5: N° DE CONTROL | J5: N° LLAVE PEATONAL | K5: ref. de pago
B6: 27 | C6: 1 | D6: PB | E6: 1 | F6: FERNANDO | G6: DOS REY | H6: ACTIVO | I6: 26A | J6: 99 | K6: 5 $ + 40bs | O6: CODIFICACION DE LLAVES
F7: DEYSY | G7: DOS REY | J7: 100
F8: CHITO | G8: DOS REY | O8: CODIFICADAS | P8: EXONERADAS | Q8: PENDIENTES | R8: NUEVAS | S8: TOTAL | T8: GASTOS [$] | U8: RECAUDADO [$]
F9: DAYANA | G9: DOS REY | O9: 225 | P9: 30 | Q9: 0 | R9: 7 | S9: =O9-P9-Q9-R9 -> 188 | T9: 28.6 | U9: =(S9*3)-T9 -> 535.4 | X9: =38.67*3 -> 116.01
X10: =115-116.01 -> -1.01
D12: PB | E12: 3 | F12: ROSARIO | G12: ACOSTA | H12: ACTIVO | I12: 199A | J12: 166/167 | K12: 5 | U12: =U9-501 -> 34.4 | W12: =U9-S9 -> 347.4
F13: RODLANIER | G13: PAMELÁ | U13: =U12*38.67 -> 1330.248
U14: =U13-747.92 -> 582.328
B15: 27 | C15: 1 | D15: 1 | E15: 101 | F15: LIGIA (DE) | G15: ISTURIZ
D17: 1 | E17: 102 | F17: FLOR | G17: HERNÁNDEZ
F18: MARIO | G18: HERNÁNDEZ | H18: BLOQUEADO | I18: 53B
D20: 1 | E20: 104 | F20: ARTURO | G20: BORRERO | H20: ACTIVO | I20: 35A | J20: 204 / 205 | K20: 18153 | O20: CODIFICACION DE LLAVES
F21: Arturo | G21: Borrero | J21: 411/412/413/414 | K21: pendiente
O22: CODIFICADAS | P22: EXONERADAS | Q22: PENDIENTES | R22: NUEVAS | S22: TOTAL | T22: GASTOS [$] | U22: RECAUDADO [$]
O23: =309-225 -> 84 | P23: 4 | Q23: 3 | R23: 1 | S23: =O23-P23-Q23-R23 -> 76 | T23: 0 | U23: =(S23*3)-T23 -> 228
B25: 27 | C25: 1 | D25: 2 | E25: 201 | F25: MAYDE | G25: MADURO | H25: ACTIVO | I25: 245A | J25: 144 | K25: exonerada
F26: MERCEDES | G26: MADURO | J26: 141 | K26: exonerada | U26: =U23-180 -> 48
F27: CARLOS | G27: MADURO | J27: 145 | K27: exonerada | U27: =U26*39 -> 1872
F28: TOMÁS | G28: MADURO | J28: 90 | K28: 7122 | O28: llave 181 señor Jesús plomero | P28: cancelo 3$ | U28: =U27-700 -> 1172 | W28: =115*3 -> 345 | X28: =863-345 -> 518
F29: ARTURO | G29: MADURO | H29: ACTIVO | I29: 244A | J29: 142 | K29: exonerada | U29: =U28-518 -> 654
F30: ARTURO | G30: MADURO | H30: ACTIVO | I30: 58B
F31: IAN | G31: CHIVICO | J31: 143 | K31: exonerada
B33: 27 | C33: 1 | D33: 2 | E33: 202 | F33: CARLOS | G33: MORALES | H33: ACTIVO | I33: 216A | J33: 277 | K33: pago cuenta porton
F34: GLADYS | G34: BICHOF
F35: IDOSELVA | G35: MORALES | H35: ACTIVO | I35: 83B | J35: 276 | K35: pago a cuenta del portón
D37: 2 | E37: 204 | F37: AMARILIS | G37: GUTIÉRREZ | H37: ACTIVO | I37: 96A
F38: ANAIBEL | G38: GUTIÉRREZ
G39: GUTIÉRREZ
B41: 27 | C41: 1 | D41: 3 | E41: 301 | F41: NOHEMÍ | G41: HERNÁNDEZ | H41: ACTIVO | I41: 43A | J41: 22 | K41: 2$+ 39Bs
F42: NOHEMÍ | G42: HERNÁNDEZ (HIJA) | H42: SUSPENDIDO | I42: 44A
D44: 3 | E44: 302 | F44: NELSON | G44: ISTURIZ | H44: BLOQUEADO | I44: 225A
F45: NELSON | G45: ISTURIZ (HIJO) | H45: BLOQUEADO | I45: 226A
F46: GUILLERMO | G46: ISTURIZ
D48: 3 | E48: 304 | F48: MARY | G48: ELÍSEO | H48: ACTIVO | I48: 126A
F49: MIREYA | G49: ELÍSEO | J49: 20 | K49: 43769
F50: ANTONIO | G50: ELÍSEO | J50: 21
F51: GABRIEL | G51: ELÍSEO | H51: ACTIVO | I51: 51A
B53: 27 | C53: 1 | D53: 4 | E53: 401 | F53: VACÍO
D55: 4 | E55: 402 | F55: AURISTELA | G55: GONCALVEZ | H55: ACTIVO | I55: 75A | J55: 285 | K55: 3
F56: JOSÉ | G56: GONCALVEZ | H56: ACTIVO | I56: 76A
F57: JORNEY | G57: GONCALVEZ | J57: 3/415 | K57: 9975
F58: albania | G58: lara | J58: 4
F59: javier | G59: sousa | J59: 5 | K59: 114bs efec
D61: 4 | E61: 404 | F61: CAROLINA | G61: OCHOA | J61: 187 | K61: 6
F62: MARÍA | G62: OCHOA | J62: 188
B65: 27 | C65: 2 | D65: PB | E65: 1 | F65: MICHAEL | G65: TERIUS | H65: BLOQUEADO | I65: 213A | J65: 405/406/407 | K65: pendiente
F66: LEIDIS | G66: TERIUS
F67: OMAIRA | G67: TERIUS
D70: PB | E70: 2 | F70: JOSÉ | G70: CARVAJAL (HIJO) | H70: ACTIVO | I70: 198A
F71: ELENA | G71: Baez | J71: 247 | K71: 3
F72: JOEL | G72: CARVAJAL | H72: ACTIVO | I72: 71B
F73: EVELIN | G73: CARVAJAL | J73: 248 | K73: 2$+ 40bs
F74: JOSE | G74: CARVAJAL | H74: SUSPENDIDO | I74: 219A
D76: PB | E76: 3 | F76: JOSEILA | G76: LUGO
F77: AURA | G77: MARCHAN | J77: 36 | K77: exonerada
F78: FELICIA | G78: LUGO | H78: ACTIVO | I78: 97A | J78: 23 | K78: exonerada
F79: FELICIA | G79: LUGO | H79: ACTIVO | I79: 72B
F80: FELICIA | G80: LUGO | H80: ACTIVO | I80: 124B
F81: WILLY | G81: SIVILA | H81: ACTIVO | I81: 12B
D83: PB | E83: 4 | F83: Yesica | G83: Nuevos | H83: ACTIVO | I83: 203B | J83: 380381 | K83: Nuevas
J85: 234
B87: 27 | C87: 2 | D87: 1 | E87: 101 | F87: MAMERTO | G87: IRRAUSQUIN | H87: SUSPENDIDO | I87: 27A
F88: YADITZA | G88: IRRAUSQUIN | H88: ACTIVO | I88: 15A | J88: 182 | K88: 35195 (Banesco )
F89: GLADIS | G89: IRRAUSQUIN | J89: 183
F90: YANIRA | G90: IRRAUSQUIN | J90: 311 | K90: 4722
F91: NATALY | G91: IRRAUSQUIN
F92: LISET | G92: IRRAUSQUIN
D94: 1 | E94: 102 | F94: MARIA | G94: PEREIRA | J94: 33 | K94: 3
F95: MARIA A. | G95: RANDEL
F96: CARLOS | G96: MELÉNDEZ
D98: 1 | E98: 103 | F98: ARELIS | G98: HERNÁNDEZ | J98: 201 | K98: exonerada
F99: WILVER | G99: MORALES | H99: BLOQUEADO
F100: ARON | G100: HERNÁNDEZ
F101: ARIANA | G101: HERNÁNDEZ
B103: 27 | C103: 2 | D103: 2 | E103: 201 | F103: EDGARDO | G103: IBARRA | H103: ACTIVO | I103: 38A
F104: JACKSON | G104: HERNÁNDEZ
F105: ILSEN | G105: IBARRA
F106: IRMA | G106: CURBANIS | J106: 146 | K106: 3
F107: LISETTE | G107: IBARRA | H107: ACTIVO | I107: 191A | J107: 376 | K107: 945 bs
F108: LISETTE | G108: IBARRA | H108: ACTIVO | I108: 140B | J108: 377
F109: Alexander | G109: Escalante | I109: 211B | J109: 378
D111: 2 | E111: 202 | F111: ALONZO | G111: GUEDEZ | H111: ACTIVO | I111: 53A
F112: AMILCAR | G112: GUEDEZ
F113: OSCAR | G113: ARROYO | H113: ACTIVO
F114: EGLEÉ | G114: GÓMEZ
F115: FABIOLA | G115: GUEDEZ | J115: 288 | K115: 90723
F116: DAFNE | G116: ARROYO | J116: 287
D118: 2 | E118: 203 | F118: YADIRA | G118: VEGA | J118: 215 / 216 | K118: 52709
F119: WALNER | G119: VEGA
F120: TERESA | G120: VERA
B122: 27 | C122: 2 | D122: 3 | E122: 301 | F122: Deyani | G122: barreto | J122: 434/ 435 | K122: pendiente
D125: 3 | E125: 302 | F125: GREGORIO | G125: ZAMBRANO | H125: ACTIVO | I125: 243A
F126: EDUARDO | G126: ZAMBRANO
F127: ALICIA | G127: ZAMBRANO
D129: 3 | E129: 303 | F129: HUGO | G129: URUBURU | H129: ACTIVO | I129: 32A | J129: 74 | K129: 6
...

Sheet Hoja 6

Sheet Lista de receptores
B3: Receptor A
B4: Nº | C4: Nombre | D4: Apellido | E4: Estatus
B5: 1A | C5: {=IFNA(VLOOKUP(B5,{'DATA DE CONTROLES Y LLAVES'!I$6:I1000,'DATA DE CONTROLES Y LLAVES'!F$6:F1000},2,FALSE),"")} -> DANIEL | D5: {=IFNA(VLOOKUP(B5,{'DATA DE CONTROLES Y LLAVES'!I$6:I1000,'DATA DE CONTROLES Y LLAVES'!G$6:G1000},2,FALSE),"")} -> FERNÁNDEZ | E5: ACTIVO
B6: 2A | C6: {=IFNA(VLOOKUP(B6,{'DATA DE CONTROLES Y LLAVES'!I$6:I1000,'DATA DE CONTROLES Y LLAVES'!F$6:F1000},2,FALSE),"")} | D6: {=IFNA(VLOOKUP(B6,{'DATA DE CONTROLES Y LLAVES'!I$6:I1000,'DATA DE CONTROLES Y LLAVES'!G$6:G1000},2,FALSE),"")} | E6: BLOQUEADO
B7: 3a | C7: {=IFNA(VLOOKUP(B7,{'DATA DE CONTROLES Y LLAVES'!I$6:I1000,'DATA DE CONTROLES Y LLAVES'!F$6:F1000},2,FALSE),"")} -> JOSEFINA | D7: {=IFNA(VLOOKUP(B7,{'DATA DE CONTROLES Y LLAVES'!I$6:I1000,'DATA DE CONTROLES Y LLAVES'!G$6:G1000},2,FALSE),"")} -> FERNÁNDEZ | E7: ACTIVO
B8: 4a | C8: {=IFNA(VLOOKUP(B8,{'DATA DE CONTROLES Y LLAVES'!I$6:I1000,'DATA DE CONTROLES Y LLAVES'!F$6:F1000},2,FALSE),"")} -> HAIDEÉ | D8: {=IFNA(VLOOKUP(B8,{'DATA DE CONTROLES Y LLAVES'!I$6:I1000,'DATA DE CONTROLES Y LLAVES'!G$6:G1000},2,FALSE),"")} -> FALCÓN | E8: ACTIVO
B9: 5a | C9: {=IFNA(VLOOKUP(B9,{'DATA DE CONTROLES Y LLAVES'!I$6:I1000,'DATA DE CONTROLES Y LLAVES'!F$6:F1000},2,FALSE),"")} -> JOSÉ | D9: {=IFNA(VLOOKUP(B9,{'DATA DE CONTROLES Y LLAVES'!I$6:I1000,'DATA DE CONTROLES Y LLAVES'!G$6:G1000},2,FALSE),"")} -> ACOSTA | E9: ACTIVO
B10: 6a | C10: {=IFNA(VLOOKUP(B10,{'DATA DE CONTROLES Y LLAVES'!I$6:I1000,'DATA DE CONTROLES Y LLAVES'!F$6:F1000},2,FALSE),"")} -> VICTOR | D10: {=IFNA(VLOOKUP(B10,{'DATA DE CONTROLES Y LLAVES'!I$6:I1000,'DATA DE CONTROLES Y LLAVES'!G$6:G1000},2,FALSE),"")} -> VIEIRA | E10: BLOQUEADO
B11: 7a | C11: {=IFNA(VLOOKUP(B11,{'DATA DE CONTROLES Y LLAVES'!I$6:I1000,'DATA DE CONTROLES Y LLAVES'!F$6:F1000},2,FALSE),"")} -> DENISE | D11: {=IFNA(VLOOKUP(B11,{'DATA DE CONTROLES Y LLAVES'!I$6:I1000,'DATA DE CONTROLES Y LLAVES'!G$6:G1000},2,FALSE),"")} -> ISTURIZ | E11: BLOQUEADO
B12: 8a | C12: {=IFNA(VLOOKUP(B12,{'DATA DE CONTROLES Y LLAVES'!I$6:I1000,'DATA DE CONTROLES Y LLAVES'!F$6:F1000},2,FALSE),"")} | D12: {=IFNA(VLOOKUP(B12,{'DATA DE CONTROLES Y LLAVES'!I$6:I1000,'DATA DE CONTROLES Y LLAVES'!G$6:G1000},2,FALSE),"")} | E12: ACTIVO
B13: 9a | C13: {=IFNA(VLOOKUP(B13,{'DATA DE CONTROLES Y LLAVES'!I$6:I1000,'DATA DE CONTROLES Y LLAVES'!F$6:F1000},2,FALSE),"")} | D13: {=IFNA(VLOOKUP(B13,{'DATA DE CONTROLES Y LLAVES'!I$6:I1000,'DATA DE CONTROLES Y LLAVES'!G$6:G1000},2,FALSE),"")} | E13: ACTIVO
B14: 10a | C14: {=IFNA(VLOOKUP(B14,{'DATA DE CONTROLES Y LLAVES'!I$6:I1000,'DATA DE CONTROLES Y LLAVES'!F$6:F1000},2,FALSE),"")} -> YELITZA | D14: {=IFNA(VLOOKUP(B14,{'DATA DE CONTROLES Y LLAVES'!I$6:I1000,'DATA DE CONTROLES Y LLAVES'!G$6:G1000},2,FALSE),"")} -> BIANCO | E14: ACTIVO
B15: 11a | C15: {=IFNA(VLOOKUP(B15,{'DATA DE CONTROLES Y LLAVES'!I$6:I1000,'DATA DE CONTROLES Y LLAVES'!F$6:F1000},2,FALSE),"")} -> LUISA | D15: {=IFNA(VLOOKUP(B15,{'DATA DE CONTROLES Y LLAVES'!I$6:I1000,'DATA DE CONTROLES Y LLAVES'!G$6:G1000},2,FALSE),"")} -> GARCÍA | E15: ACTIVO
B16: 12a | C16: {=IFNA(VLOOKUP(B16,{'DATA DE CONTROLES Y LLAVES'!I$6:I1000,'DATA DE CONTROLES Y LLAVES'!F$6:F1000},2,FALSE),"")} -> TAIZ | D16: {=IFNA(VLOOKUP(B16,{'DATA DE CONTROLES Y LLAVES'!I$6:I1000,'DATA DE CONTROLES Y LLAVES'!G$6:G1000},2,FALSE),"")} -> CONTRERAS | E16: ACTIVO
B17: 13a | C17: {=IFNA(VLOOKUP(B17,{'DATA DE CONTROLES Y LLAVES'!I$6:I1000,'DATA DE CONTROLES Y LLAVES'!F$6:F1000},2,FALSE),"")} -> DORIS | D17: {=IFNA(VLOOKUP(B17,{'DATA DE CONTROLES Y LLAVES'!I$6:I1000,'DATA DE CONTROLES Y LLAVES'!G$6:G1000},2,FALSE),"")} -> SANCHEZ | E17: BLOQUEADO
B18: 14a | C18: {=IFNA(VLOOKUP(B18,{'DATA DE CONTROLES Y LLAVES'!I$6:I1000,'DATA DE CONTROLES Y LLAVES'!F$6:F1000},2,FALSE),"")} | D18: {=IFNA(VLOOKUP(B18,{'DATA DE CONTROLES Y LLAVES'!I$6:I1000,'DATA DE CONTROLES Y LLAVES'!G$6:G1000},2,FALSE),"")} | E18: BLOQUEADO
B19: 15a | C19: {=IFNA(VLOOKUP(B19,{'DATA DE CONTROLES Y LLAVES'!I$6:I1000,'DATA DE CONTROLES Y LLAVES'!F$6:F1000},2,FALSE),"")} -> YADITZA | D19: {=IFNA(VLOOKUP(B19,{'DATA DE CONTROLES Y LLAVES'!I$6:I1000,'DATA DE CONTROLES Y LLAVES'!G$6:G1000},2,FALSE),"")} -> IRRAUSQUIN | E19: ACTIVO
B20: 16a | C20: {=IFNA(VLOOKUP(B20,{'DATA DE CONTROLES Y LLAVES'!I$6:I1000,'DATA DE CONTROLES Y LLAVES'!F$6:F1000},2,FALSE),"")} -> GLEISYS | D20: {=IFNA(VLOOKUP(B20,{'DATA DE CONTROLES Y LLAVES'!I$6:I1000,'DATA DE CONTROLES Y LLAVES'!G$6:G1000},2,FALSE),"")} -> CHAVEZ | E20: ACTIVO
B21: 17a | C21: {=IFNA(VLOOKUP(B21,{'DATA DE CONTROLES Y LLAVES'!I$6:I1000,'DATA DE CONTROLES Y LLAVES'!F$6:F1000},2,FALSE),"")} -> VICTOR | D21: {=IFNA(VLOOKUP(B21,{'DATA DE CONTROLES Y LLAVES'!I$6:I1000,'DATA DE CONTROLES Y LLAVES'!G$6:G1000},2,FALSE),"")} -> VERAMENDI | E21: ACTIVO
B22: 18a | C22: {=IFNA(VLOOKUP(B22,{'DATA DE CONTROLES Y LLAVES'!I$6:I1000,'DATA DE CONTROLES Y LLAVES'!F$6:F1000},2,FALSE),"")} -> VALENTINA | D22: {=IFNA(VLOOKUP(B22,{'DATA DE CONTROLES Y LLAVES'!I$6:I1000,'DATA DE CONTROLES Y LLAVES'!G$6:G1000},2,FALSE),"")} -> ESPINOZA | E22: ACTIVO
B23: 19a | C23: {=IFNA(VLOOKUP(B23,{'DATA DE CONTROLES Y LLAVES'!I$6:I1000,'DATA DE CONTROLES Y LLAVES'!F$6:F1000},2,FALSE),"")} -> KEIZLER | D23: {=IFNA(VLOOKUP(B23,{'DATA DE CONTROLES Y LLAVES'!I$6:I1000,'DATA DE CONTROLES Y LLAVES'!G$6:G1000},2,FALSE),"")} -> URBINA | E23: ACTIVO
B24: 20a | C24: {=IFNA(VLOOKUP(B24,{'DATA DE CONTROLES Y LLAVES'!I$6:I1000,'DATA DE CONTROLES Y LLAVES'!F$6:F1000},2,FALSE),"")} -> VICTOR | D24: {=IFNA(VLOOKUP(B24,{'DATA DE CONTROLES Y LLAVES'!I$6:I1000,'DATA DE CONTROLES Y LLAVES'!G$6:G1000},2,FALSE),"")} -> PEREZ | E24: ACTIVO
B25: 21a | C25: {=IFNA(VLOOKUP(B25,{'DATA DE CONTROLES Y LLAVES'!I$6:I1000,'DATA DE CONTROLES Y LLAVES'!F$6:F1000},2,FALSE),"")} -> JEIMI | D25: {=IFNA(VLOOKUP(B25,{'DATA DE CONTROLES Y LLAVES'!I$6:I1000,'DATA DE CONTROLES Y LLAVES'!G$6:G1000},2,FALSE),"")} -> DIAZ | E25: ACTIVO
B26: 22a | C26: {=IFNA(VLOOKUP(B26,{'DATA DE CONTROLES Y LLAVES'!I$6:I1000,'DATA DE CONTROLES Y LLAVES'!F$6:F1000},2,FALSE),"")} -> JOSÉ | D26: {=IFNA(VLOOKUP(B26,{'DATA DE CONTROLES Y LLAVES'!I$6:I1000,'DATA DE CONTROLES Y LLAVES'!G$6:G1000},2,FALSE),"")} -> VÁSQUEZ | E26: ACTIVO
B27: 23a | C27: {=IFNA(VLOOKUP(B27,{'DATA DE CONTROLES Y LLAVES'!I$6:I1000,'DATA DE CONTROLES Y LLAVES'!F$6:F1000},2,FALSE),"")} -> MARUJA | D27: {=IFNA(VLOOKUP(B27,{'DATA DE CONTROLES Y LLAVES'!I$6:I1000,'DATA DE CONTROLES Y LLAVES'!G$6:G1000},2,FALSE),"")} -> MARRERO | E27: BLOQUEADO
B28: 24a | C28: {=IFNA(VLOOKUP(B28,{'DATA DE CONTROLES Y LLAVES'!I$6:I1000,'DATA DE CONTROLES Y LLAVES'!F$6:F1000},2,FALSE),"")} -> RAMSES | D28: {=IFNA(VLOOKUP(B28,{'DATA DE CONTROLES Y LLAVES'!I$6:I1000,'DATA DE CONTROLES Y LLAVES'!G$6:G1000},2,FALSE),"")} -> ROJAS | E28: BLOQUEADO
B29: 25a | C29: {=IFNA(VLOOKUP(B29,{'DATA DE CONTROLES Y LLAVES'!I$6:I1000,'DATA DE CONTROLES Y LLAVES'!F$6:F1000},2,FALSE),"")} -> JOEL | D29: {=IFNA(VLOOKUP(B29,{'DATA DE CONTROLES Y LLAVES'!I$6:I1000,'DATA DE CONTROLES Y LLAVES'!G$6:G1000},2,FALSE),"")} -> MARTINEZ | E29: BLOQUEADO
B30: 26a | C30: {=IFNA(VLOOKUP(B30,{'DATA DE CONTROLES Y LLAVES'!I$6:I1000,'DATA DE CONTROLES Y LLAVES'!F$6:F1000},2,FALSE),"")} -> FERNANDO | D30: {=IFNA(VLOOKUP(B30,{'DATA DE CONTROLES Y LLAVES'!I$6:I1000,'DATA DE CONTROLES Y LLAVES'!G$6:G1000},2,FALSE),"")} -> DOS REY | E30: ACTIVO
B31: 27a | C31: {=IFNA(VLOOKUP(B31,{'DATA DE CONTROLES Y LLAVES'!I$6:I1000,'DATA DE CONTROLES Y LLAVES'!F$6:F1000},2,FALSE),"")} -> MAMERTO | D31: {=IFNA(VLOOKUP(B31,{'DATA DE CONTROLES Y LLAVES'!I$6:I1000,'DATA DE CONTROLES Y LLAVES'!G$6:G1000},2,FALSE),"")} -> IRRAUSQUIN | E31: SUSPENDIDO
B32: 28a | C32: {=IFNA(VLOOKUP(B32,{'DATA DE CONTROLES Y LLAVES'!I$6:I1000,'DATA DE CONTROLES Y LLAVES'!F$6:F1000},2,FALSE),"")} -> EMMA | D32: {=IFNA(VLOOKUP(B32,{'DATA DE CONTROLES Y LLAVES'!I$6:I1000,'DATA DE CONTROLES Y LLAVES'!G$6:G1000},2,FALSE),"")} -> HERNÁNDEZ | E32: ACTIVO
B33: 29a | C33: {=IFNA(VLOOKUP(B33,{'DATA DE CONTROLES Y LLAVES'!I$6:I1000,'DATA DE CONTROLES Y LLAVES'!F$6:F1000},2,FALSE),"")} -> HAILER | D33: {=IFNA(VLOOKUP(B33,{'DATA DE CONTROLES Y LLAVES'!I$6:I1000,'DATA DE CONTROLES Y LLAVES'!G$6:G1000},2,FALSE),"")} -> QUERALES | E33: BLOQUEADO
B34: 30a | C34: {=IFNA(VLOOKUP(B34,{'DATA DE CONTROLES Y LLAVES'!I$6:I1000,'DATA DE CONTROLES Y LLAVES'!F$6:F1000},2,FALSE),"")} -> GLORIA | D34: {=IFNA(VLOOKUP(B34,{'DATA DE CONTROLES Y LLAVES'!I$6:I1000,'DATA DE CONTROLES Y LLAVES'!G$6:G1000},2,FALSE),"")} -> DELGADO | E34: ACTIVO
B35: 31a | C35: {=IFNA(VLOOKUP(B35,{'DATA DE CONTROLES Y LLAVES'!I$6:I1000,'DATA DE CONTROLES Y LLAVES'!F$6:F1000},2,FALSE),"")} -> DANIEL | D35: {=IFNA(VLOOKUP(B35,{'DATA DE CONTROLES Y LLAVES'!I$6:I1000,'DATA DE CONTROLES Y LLAVES'!G$6:G1000},2,FALSE),"")} -> DA COSTA | E35: ACTIVO
B36: 32a | C36: {=IFNA(VLOOKUP(B36,{'DATA DE CONTROLES Y LLAVES'!I$6:I1000,'DATA DE CONTROLES Y LLAVES'!F$6:F1000},2,FALSE),"")} -> HUGO | D36: {=IFNA(VLOOKUP(B36,{'DATA DE CONTROLES Y LLAVES'!I$6:I1000,'DATA DE CONTROLES Y LLAVES'!G$6:G1000},2,FALSE),"")} -> URUBURU | E36: ACTIVO
B37: 33a | C37: {=IFNA(VLOOKUP(B37,{'DATA DE CONTROLES Y LLAVES'!I$6:I1000,'DATA DE CONTROLES Y LLAVES'!F$6:F1000},2,FALSE),"")} -> JENIFER | D37: {=IFNA(VLOOKUP(B37,{'DATA DE CONTROLES Y LLAVES'!I$6:I1000,'DATA DE CONTROLES Y LLAVES'!G$6:G1000},2,FALSE),"")} -> URUBURU | E37: ACTIVO
B38: 34a | C38: {=IFNA(VLOOKUP(B38,{'DATA DE CONTROLES Y LLAVES'!I$6:I1000,'DATA DE CONTROLES Y LLAVES'!F$6:F1000},2,FALSE),"")} | D38: {=IFNA(VLOOKUP(B38,{'DATA DE CONTROLES Y LLAVES'!I$6:I1000,'DATA DE CONTROLES Y LLAVES'!G$6:G1000},2,FALSE),"")} | E38: ACTIVO
B39: 35a | C39: {=IFNA(VLOOKUP(B39,{'DATA DE CONTROLES Y LLAVES'!I$6:I1000,'DATA DE CONTROLES Y LLAVES'!F$6:F1000},2,FALSE),"")} -> ARTURO | D39: {=IFNA(VLOOKUP(B39,{'DATA DE CONTROLES Y LLAVES'!I$6:I1000,'DATA DE CONTROLES Y LLAVES'!G$6:G1000},2,FALSE),"")} -> BORRERO | E39: ACTIVO
B40: 36a | C40: {=IFNA(VLOOKUP(B40,{'DATA DE CONTROLES Y LLAVES'!I$6:I1000,'DATA DE CONTROLES Y LLAVES'!F$6:F1000},2,FALSE),"")} -> DULCE | D40: {=IFNA(VLOOKUP(B40,{'DATA DE CONTROLES Y LLAVES'!I$6:I1000,'DATA DE CONTROLES Y LLAVES'!G$6:G1000},2,FALSE),"")} -> MUÑOZ | E40: BLOQUEADO
B41: 37a | C41: {=IFNA(VLOOKUP(B41,{'DATA DE CONTROLES Y LLAVES'!I$6:I1000,'DATA DE CONTROLES Y LLAVES'!F$6:F1000},2,FALSE),"")} -> LORENA | D41: {=IFNA(VLOOKUP(B41,{'DATA DE CONTROLES Y LLAVES'!I$6:I1000,'DATA DE CONTROLES Y LLAVES'!G$6:G1000},2,FALSE),"")} -> GARCIA | E41: BLOQUEADO
B42: 38a | C42: {=IFNA(VLOOKUP(B42,{'DATA DE CONTROLES Y LLAVES'!I$6:I1000,'DATA DE CONTROLES Y LLAVES'!F$6:F1000},2,FALSE),"")} -> EDGARDO | D42: {=IFNA(VLOOKUP(B42,{'DATA DE CONTROLES Y LLAVES'!I$6:I1000,'DATA DE CONTROLES Y LLAVES'!G$6:G1000},2,FALSE),"")} -> IBARRA | E42: ACTIVO
B43: 39a | C43: {=IFNA(VLOOKUP(B43,{'DATA DE CONTROLES Y LLAVES'!I$6:I1000,'DATA DE CONTROLES Y LLAVES'!F$6:F1000},2,FALSE),"")} | D43: {=IFNA(VLOOKUP(B43,{'DATA DE CONTROLES Y LLAVES'!I$6:I1000,'DATA DE CONTROLES Y LLAVES'!G$6:G1000},2,FALSE),"")} | E43: ACTIVO
B44: 40a | C44: {=IFNA(VLOOKUP(B44,{'DATA DE CONTROLES Y LLAVES'!I$6:I1000,'DATA DE CONTROLES Y LLAVES'!F$6:F1000},2,FALSE),"")} -> kevin | D44: {=IFNA(VLOOKUP(B44,{'DATA DE CONTROLES Y LLAVES'!I$6:I1000,'DATA DE CONTROLES Y LLAVES'!G$6:G1000},2,FALSE),"")} -> flores | E44: ACTIVO
B45: 41a | C45: {=IFNA(VLOOKUP(B45,{'DATA DE CONTROLES Y LLAVES'!I$6:I1000,'DATA DE CONTROLES Y LLAVES'!F$6:F1000},2,FALSE),"")} -> MIRIAM | D45: {=IFNA(VLOOKUP(B45,{'DATA DE CONTROLES Y LLAVES'!I$6:I1000,'DATA DE CONTROLES Y LLAVES'!G$6:G1000},2,FALSE),"")} -> PAVÁN | E45: ACTIVO
B46: 42a | C46: {=IFNA(VLOOKUP(B46,{'DATA DE CONTROLES Y LLAVES'!I$6:I1000,'DATA DE CONTROLES Y LLAVES'!F$6:F1000},2,FALSE),"")} -> OMAR | D46: {=IFNA(VLOOKUP(B46,{'DATA DE CONTROLES Y LLAVES'!I$6:I1000,'DATA DE CONTROLES Y LLAVES'!G$6:G1000},2,FALSE),"")} -> GARCÍA | E46: BLOQUEADO
B47: 43a | C47: {=IFNA(VLOOKUP(B47,{'DATA DE CONTROLES Y LLAVES'!I$6:I1000,'DATA DE CONTROLES Y LLAVES'!F$6:F1000},2,FALSE),"")} -> NOHEMÍ | D47: {=IFNA(VLOOKUP(B47,{'DATA DE CONTROLES Y LLAVES'!I$6:I1000,'DATA DE CONTROLES Y LLAVES'!G$6:G1000},2,FALSE),"")} -> HERNÁNDEZ | E47: ACTIVO
B48: 44a | C48: {=IFNA(VLOOKUP(B48,{'DATA DE CONTROLES Y LLAVES'!I$6:I1000,'DATA DE CONTROLES Y LLAVES'!F$6:F1000},2,FALSE),"")} -> NOHEMÍ | D48: {=IFNA(VLOOKUP(B48,{'DATA DE CONTROLES Y LLAVES'!I$6:I1000,'DATA DE CONTROLES Y LLAVES'!G$6:G1000},2,FALSE),"")} -> HERNÁNDEZ (HIJA) | E48: BLOQUEADO
B49: 45a | C49: {=IFNA(VLOOKUP(B49,{'DATA DE CONTROLES Y LLAVES'!I$6:I1000,'DATA DE CONTROLES Y LLAVES'!F$6:F1000},2,FALSE),"")} -> NESTOR | D49: {=IFNA(VLOOKUP(B49,{'DATA DE CONTROLES Y LLAVES'!I$6:I1000,'DATA DE CONTROLES Y LLAVES'!G$6:G1000},2,FALSE),"")} -> MARTINEZ | E49: BLOQUEADO
B50: 46a | C50: {=IFNA(VLOOKUP(B50,{'DATA DE CONTROLES Y LLAVES'!I$6:I1000,'DATA DE CONTROLES Y LLAVES'!F$6:F1000},2,FALSE),"")} -> RAMÓN | D50: {=IFNA(VLOOKUP(B50,{'DATA DE CONTROLES Y LLAVES'!I$6:I1000,'DATA DE CONTROLES Y LLAVES'!G$6:G1000},2,FALSE),"")} -> PIÑANGO | E50: ACTIVO
B51: 47a | C51: {=IFNA(VLOOKUP(B51,{'DATA DE CONTROLES Y LLAVES'!I$6:I1000,'DATA DE CONTROLES Y LLAVES'!F$6:F1000},2,FALSE),"")} -> ROBERTO | D51: {=IFNA(VLOOKUP(B51,{'DATA DE CONTROLES Y LLAVES'!I$6:I1000,'DATA DE CONTROLES Y LLAVES'!G$6:G1000},2,FALSE),"")} -> TONITO | E51: PERDIDO
B52: 48a | C52: {=IFNA(VLOOKUP(B52,{'DATA DE CONTROLES Y LLAVES'!I$6:I1000,'DATA DE CONTROLES Y LLAVES'!F$6:F1000},2,FALSE),"")} -> hernan | D52: {=IFNA(VLOOKUP(B52,{'DATA DE CONTROLES Y LLAVES'!I$6:I1000,'DATA DE CONTROLES Y LLAVES'!G$6:G1000},2,FALSE),"")} -> Olivar | E52: ACTIVO
B53: 49a | C53: {=IFNA(VLOOKUP(B53,{'DATA DE CONTROLES Y LLAVES'!I$6:I1000,'DATA DE CONTROLES Y LLAVES'!F$6:F1000},2,FALSE),"")} -> hernan | D53: {=IFNA(VLOOKUP(B53,{'DATA DE CONTROLES Y LLAVES'!I$6:I1000,'DATA DE CONTROLES Y LLAVES'!G$6:G1000},2,FALSE),"")} -> Olivar | E53: ACTIVO
B54: 50a | C54: {=IFNA(VLOOKUP(B54,{'DATA DE CONTROLES Y LLAVES'!I$6:I1000,'DATA DE CONTROLES Y LLAVES'!F$6:F1000},2,FALSE),"")} | D54: {=IFNA(VLOOKUP(B54,{'DATA DE CONTROLES Y LLAVES'!I$6:I1000,'DATA DE CONTROLES Y LLAVES'!G$6:G1000},2,FALSE),"")} | E54: ACTIVO
B55: 51a | C55: {=IFNA(VLOOKUP(B55,{'DATA DE CONTROLES Y LLAVES'!I$6:I1000,'DATA DE CONTROLES Y LLAVES'!F$6:F1000},2,FALSE),"")} -> GABRIEL | D55: {=IFNA(VLOOKUP(B55,{'DATA DE CONTROLES Y LLAVES'!I$6:I1000,'DATA DE CONTROLES Y LLAVES'!G$6:G1000},2,FALSE),"")} -> ELÍSEO | E55: ACTIVO
B56: 52a | C56: {=IFNA(VLOOKUP(B56,{'DATA DE CONTROLES Y LLAVES'!I$6:I1000,'DATA DE CONTROLES Y LLAVES'!F$6:F1000},2,FALSE),"")} -> DENISE | D56: {=IFNA(VLOOKUP(B56,{'DATA DE CONTROLES Y LLAVES'!I$6:I1000,'DATA DE CONTROLES Y LLAVES'!G$6:G1000},2,FALSE),"")} -> ISTURIZ | E56: BLOQUEADO
B57: 53a | C57: {=IFNA(VLOOKUP(B57,{'DATA DE CONTROLES Y LLAVES'!I$6:I1000,'DATA DE CONTROLES Y LLAVES'!F$6:F1000},2,FALSE),"")} -> ALONZO | D57: {=IFNA(VLOOKUP(B57,{'DATA DE CONTROLES Y LLAVES'!I$6:I1000,'DATA DE CONTROLES Y LLAVES'!G$6:G1000},2,FALSE),"")} -> GUEDEZ | E57: BLOQUEADO
B58: 54a | C58: {=IFNA(VLOOKUP(B58,{'DATA DE CONTROLES Y LLAVES'!I$6:I1000,'DATA DE CONTROLES Y LLAVES'!F$6:F1000},2,FALSE),"")} -> PEDRO | D58: {=IFNA(VLOOKUP(B58,{'DATA DE CONTROLES Y LLAVES'!I$6:I1000,'DATA DE CONTROLES Y LLAVES'!G$6:G1000},2,FALSE),"")} -> RAMOS | E58: ACTIVO
B59: 55a | C59: {=IFNA(VLOOKUP(B59,{'DATA DE CONTROLES Y LLAVES'!I$6:I1000,'DATA DE CONTROLES Y LLAVES'!F$6:F1000},2,FALSE),"")} -> MARY (DE) | D59: {=IFNA(VLOOKUP(B59,{'DATA DE CONTROLES Y LLAVES'!I$6:I1000,'DATA DE CONTROLES Y LLAVES'!G$6:G1000},2,FALSE),"")} -> RAMOS | E59: ACTIVO
B60: 56a | C60: {=IFNA(VLOOKUP(B60,{'DATA DE CONTROLES Y LLAVES'!I$6:I1000,'DATA DE CONTROLES Y LLAVES'!F$6:F1000},2,FALSE),"")} -> PEDRO (PAPA) | D60: {=IFNA(VLOOKUP(B60,{'DATA DE CONTROLES Y LLAVES'!I$6:I1000,'DATA DE CONTROLES Y LLAVES'!G$6:G1000},2,FALSE),"")} -> RAMOS | E60: ACTIVO
B61: 57a | C61: {=IFNA(VLOOKUP(B61,{'DATA DE CONTROLES Y LLAVES'!I$6:I1000,'DATA DE CONTROLES Y LLAVES'!F$6:F1000},2,FALSE),"")} -> Reinaldo | D61: {=IFNA(VLOOKUP(B61,{'DATA DE CONTROLES Y LLAVES'!I$6:I1000,'DATA DE CONTROLES Y LLAVES'!G$6:G1000},2,FALSE),"")} -> Arenas | E61: ACTIVO
B62: 58a | C62: {=IFNA(VLOOKUP(B62,{'DATA DE CONTROLES Y LLAVES'!I$6:I1000,'DATA DE CONTROLES Y LLAVES'!F$6:F1000},2,FALSE),"")} -> MAYLIN | D62: {=IFNA(VLOOKUP(B62,{'DATA DE CONTROLES Y LLAVES'!I$6:I1000,'DATA DE CONTROLES Y LLAVES'!G$6:G1000},2,FALSE),"")} -> GARCÍA | E62: ACTIVO
B63: 59a | C63: {=IFNA(VLOOKUP(B63,{'DATA DE CONTROLES Y LLAVES'!I$6:I1000,'DATA DE CONTROLES Y LLAVES'!F$6:F1000},2,FALSE),"")} -> carolina | D63: {=IFNA(VLOOKUP(B63,{'DATA DE CONTROLES Y LLAVES'!I$6:I1000,'DATA DE CONTROLES Y LLAVES'!G$6:G1000},2,FALSE),"")} -> Piñate | E63: ACTIVO
B64: 60a | C64: {=IFNA(VLOOKUP(B64,{'DATA DE CONTROLES Y LLAVES'!I$6:I1000,'DATA DE CONTROLES Y LLAVES'!F$6:F1000},2,FALSE),"")} -> Angélica | D64: {=IFNA(VLOOKUP(B64,{'DATA DE CONTROLES Y LLAVES'!I$6:I1000,'DATA DE CONTROLES Y LLAVES'!G$6:G1000},2,FALSE),"")} -> Ibarra | E64: ACTIVO
B65: 61a | C65: {=IFNA(VLOOKUP(B65,{'DATA DE CONTROLES Y LLAVES'!I$6:I1000,'DATA DE CONTROLES Y LLAVES'!F$6:F1000},2,FALSE),"")} -> FRAN | D65: {=IFNA(VLOOKUP(B65,{'DATA DE CONTROLES Y LLAVES'!I$6:I1000,'DATA DE CONTROLES Y LLAVES'!G$6:G1000},2,FALSE),"")} -> MENDOZA | E65: ACTIVO
B66: 62a | C66: {=IFNA(VLOOKUP(B66,{'DATA DE CONTROLES Y LLAVES'!I$6:I1000,'DATA DE CONTROLES Y LLAVES'!F$6:F1000},2,FALSE),"")} -> PEDRO | D66: {=IFNA(VLOOKUP(B66,{'DATA DE CONTROLES Y LLAVES'!I$6:I1000,'DATA DE CONTROLES Y LLAVES'!G$6:G1000},2,FALSE),"")} -> PIÑATE | E66: ACTIVO
B67: 63a | C67: {=IFNA(VLOOKUP(B67,{'DATA DE CONTROLES Y LLAVES'!I$6:I1000,'DATA DE CONTROLES Y LLAVES'!F$6:F1000},2,FALSE),"")} -> DINO | D67: {=IFNA(VLOOKUP(B67,{'DATA DE CONTROLES Y LLAVES'!I$6:I1000,'DATA DE CONTROLES Y LLAVES'!G$6:G1000},2,FALSE),"")} -> BIANCO | E67: ACTIVO
B68: 64a | C68: {=IFNA(VLOOKUP(B68,{'DATA DE CONTROLES Y LLAVES'!I$6:I1000,'DATA DE CONTROLES Y LLAVES'!F$6:F1000},2,FALSE),"")} -> ARELIS | D68: {=IFNA(VLOOKUP(B68,{'DATA DE CONTROLES Y LLAVES'!I$6:I1000,'DATA DE CONTROLES Y LLAVES'!G$6:G1000},2,FALSE),"")} -> PIÑATE | E68: ACTIVO
B69: 65a | C69: {=IFNA(VLOOKUP(B69,{'DATA DE CONTROLES Y LLAVES'!I$6:I1000,'DATA DE CONTROLES Y LLAVES'!F$6:F1000},2,FALSE),"")} -> EDGARDO | D69: {=IFNA(VLOOKUP(B69,{'DATA DE CONTROLES Y LLAVES'!I$6:I1000,'DATA DE CONTROLES Y LLAVES'!G$6:G1000},2,FALSE),"")} -> ACEITUNO | E69: ACTIVO
B70: 66a | C70: {=IFNA(VLOOKUP(B70,{'DATA DE CONTROLES Y LLAVES'!I$6:I1000,'DATA DE CONTROLES Y LLAVES'!F$6:F1000},2,FALSE),"")} -> BELKIS | D70: {=IFNA(VLOOKUP(B70,{'DATA DE CONTROLES Y LLAVES'!I$6:I1000,'DATA DE CONTROLES Y LLAVES'!G$6:G1000},2,FALSE),"")} -> BARRAEZ | E70: ACTIVO
B71: 67a | C71: {=IFNA(VLOOKUP(B71,{'DATA DE CONTROLES Y LLAVES'!I$6:I1000,'DATA DE CONTROLES Y LLAVES'!F$6:F1000},2,FALSE),"")} -> JACKELINE | D71: {=IFNA(VLOOKUP(B71,{'DATA DE CONTROLES Y LLAVES'!I$6:I1000,'DATA DE CONTROLES Y LLAVES'!G$6:G1000},2,FALSE),"")} -> ORTEGA | E71: ACTIVO
B72: 68a | C72: {=IFNA(VLOOKUP(B72,{'DATA DE CONTROLES Y LLAVES'!I$6:I1000,'DATA DE CONTROLES Y LLAVES'!F$6:F1000},2,FALSE),"")} -> DANIELA | D72: {=IFNA(VLOOKUP(B72,{'DATA DE CONTROLES Y LLAVES'!I$6:I1000,'DATA DE CONTROLES Y LLAVES'!G$6:G1000},2,FALSE),"")} -> MARTÍNEZ | E72: BLOQUEADO
B73: 69a | C73: {=IFNA(VLOOKUP(B73,{'DATA DE CONTROLES Y LLAVES'!I$6:I1000,'DATA DE CONTROLES Y LLAVES'!F$6:F1000},2,FALSE),"")} -> JOSÉ | D73: {=IFNA(VLOOKUP(B73,{'DATA DE CONTROLES Y LLAVES'!I$6:I1000,'DATA DE CONTROLES Y LLAVES'!G$6:G1000},2,FALSE),"")} -> MARTÍNEZ D. | E73: ACTIVO
B74: 70a | C74: {=IFNA(VLOOKUP(B74,{'DATA DE CONTROLES Y LLAVES'!I$6:I1000,'DATA DE CONTROLES Y LLAVES'!F$6:F1000},2,FALSE),"")} -> CARLOS | D74: {=IFNA(VLOOKUP(B74,{'DATA DE CONTROLES Y LLAVES'!I$6:I1000,'DATA DE CONTROLES Y LLAVES'!G$6:G1000},2,FALSE),"")} -> SÁNCHEZ | E74: ACTIVO
B75: 71a | C75: {=IFNA(VLOOKUP(B75,{'DATA DE CONTROLES Y LLAVES'!I$6:I1000,'DATA DE CONTROLES Y LLAVES'!F$6:F1000},2,FALSE),"")} -> BEATRIZ | D75: {=IFNA(VLOOKUP(B75,{'DATA DE CONTROLES Y LLAVES'!I$6:I1000,'DATA DE CONTROLES Y LLAVES'!G$6:G1000},2,FALSE),"")} -> RODRÍGUEZ | E75: ACTIVO
B76: 72a | C76: {=IFNA(VLOOKUP(B76,{'DATA DE CONTROLES Y LLAVES'!I$6:I1000,'DATA DE CONTROLES Y LLAVES'!F$6:F1000},2,FALSE),"")} -> Alvaro (hijo) | D76: {=IFNA(VLOOKUP(B76,{'DATA DE CONTROLES Y LLAVES'!I$6:I1000,'DATA DE CONTROLES Y LLAVES'!G$6:G1000},2,FALSE),"")} -> Parra | E76: ACTIVO
B77: 73a | C77: {=IFNA(VLOOKUP(B77,{'DATA DE CONTROLES Y LLAVES'!I$6:I1000,'DATA DE CONTROLES Y LLAVES'!F$6:F1000},2,FALSE),"")} -> FLOR | D77: {=IFNA(VLOOKUP(B77,{'DATA DE CONTROLES Y LLAVES'!I$6:I1000,'DATA DE CONTROLES Y LLAVES'!G$6:G1000},2,FALSE),"")} -> PIÑANGO | E77: ACTIVO
B78: 74a | C78: {=IFNA(VLOOKUP(B78,{'DATA DE CONTROLES Y LLAVES'!I$6:I1000,'DATA DE CONTROLES Y LLAVES'!F$6:F1000},2,FALSE),"")} -> MARIALIS | D78: {=IFNA(VLOOKUP(B78,{'DATA DE CONTROLES Y LLAVES'!I$6:I1000,'DATA DE CONTROLES Y LLAVES'!G$6:G1000},2,FALSE),"")} -> SMAIN | E78: BLOQUEADO
B79: 75a | C79: {=IFNA(VLOOKUP(B79,{'DATA DE CONTROLES Y LLAVES'!I$6:I1000,'DATA DE CONTROLES Y LLAVES'!F$6:F1000},2,FALSE),"")} -> AURISTELA | D79: {=IFNA(VLOOKUP(B79,{'DATA DE CONTROLES Y LLAVES'!I$6:I1000,'DATA DE CONTROLES Y LLAVES'!G$6:G1000},2,FALSE),"")} -> GONCALVEZ | E79: BLOQUEADO
B80: 76a | C80: {=IFNA(VLOOKUP(B80,{'DATA DE CONTROLES Y LLAVES'!I$6:I1000,'DATA DE CONTROLES Y LLAVES'!F$6:F1000},2,FALSE),"")} -> JOSÉ | D80: {=IFNA(VLOOKUP(B80,{'DATA DE CONTROLES Y LLAVES'!I$6:I1000,'DATA DE CONTROLES Y LLAVES'!G$6:G1000},2,FALSE),"")} -> GONCALVEZ | E80: ACTIVO
B81: 77a | C81: {=IFNA(VLOOKUP(B81,{'DATA DE CONTROLES Y LLAVES'!I$6:I1000,'DATA DE CONTROLES Y LLAVES'!F$6:F1000},2,FALSE),"")} -> LEONARDO | D81: {=IFNA(VLOOKUP(B81,{'DATA DE CONTROLES Y LLAVES'!I$6:I1000,'DATA DE CONTROLES Y LLAVES'!G$6:G1000},2,FALSE),"")} -> CABALLERO | E81: BLOQUEADO
B82: 78a | C82: {=IFNA(VLOOKUP(B82,{'DATA DE CONTROLES Y LLAVES'!I$6:I1000,'DATA DE CONTROLES Y LLAVES'!F$6:F1000},2,FALSE),"")} -> ALVARO | D82: {=IFNA(VLOOKUP(B82,{'DATA DE CONTROLES Y LLAVES'!I$6:I1000,'DATA DE CONTROLES Y LLAVES'!G$6:G1000},2,FALSE),"")} -> PARRA | E82: PERDIDO
B83: 79a | C83: {=IFNA(VLOOKUP(B83,{'DATA DE CONTROLES Y LLAVES'!I$6:I1000,'DATA DE CONTROLES Y LLAVES'!F$6:F1000},2,FALSE),"")} | D83: {=IFNA(VLOOKUP(B83,{'DATA DE CONTROLES Y LLAVES'!I$6:I1000,'DATA DE CONTROLES Y LLAVES'!G$6:G1000},2,FALSE),"")} | E83: BLOQUEADO
B84: 80a | C84: {=IFNA(VLOOKUP(B84,{'DATA DE CONTROLES Y LLAVES'!I$6:I1000,'DATA DE CONTROLES Y LLAVES'!F$6:F1000},2,FALSE),"")} -> JANETTE | D84: {=IFNA(VLOOKUP(B84,{'DATA DE CONTROLES Y LLAVES'!I$6:I1000,'DATA DE CONTROLES Y LLAVES'!G$6:G1000},2,FALSE),"")} -> HERNÁNDEZ | E84: BLOQUEADO
B85: 81a | C85: {=IFNA(VLOOKUP(B85,{'DATA DE CONTROLES Y LLAVES'!I$6:I1000,'DATA DE CONTROLES Y LLAVES'!F$6:F1000},2,FALSE),"")} | D85: {=IFNA(VLOOKUP(B85,{'DATA DE CONTROLES Y LLAVES'!I$6:I1000,'DATA DE CONTROLES Y LLAVES'!G$6:G1000},2,FALSE),"")} | E85: ACTIVO
B86: 82a | C86: {=IFNA(VLOOKUP(B86,{'DATA DE CONTROLES Y LLAVES'!I$6:I1000,'DATA DE CONTROLES Y LLAVES'!F$6:F1000},2,FALSE),"")} -> VICTOR | D86: {=IFNA(VLOOKUP(B86,{'DATA DE CONTROLES Y LLAVES'!I$6:I1000,'DATA DE CONTROLES Y LLAVES'!G$6:G1000},2,FALSE),"")} -> VIEIRA | E86: ACTIVO
B87: 83a | C87: {=IFNA(VLOOKUP(B87,{'DATA DE CONTROLES Y LLAVES'!I$6:I1000,'DATA DE CONTROLES Y LLAVES'!F$6:F1000},2,FALSE),"")} -> ANGELO | D87: {=IFNA(VLOOKUP(B87,{'DATA DE CONTROLES Y LLAVES'!I$6:I1000,'DATA DE CONTROLES Y LLAVES'!G$6:G1000},2,FALSE),"")} -> BIANCO | E87: ACTIVO
B88: 84a | C88: {=IFNA(VLOOKUP(B88,{'DATA DE CONTROLES Y LLAVES'!I$6:I1000,'DATA DE CONTROLES Y LLAVES'!F$6:F1000},2,FALSE),"")} -> ELVIS | D88: {=IFNA(VLOOKUP(B88,{'DATA DE CONTROLES Y LLAVES'!I$6:I1000,'DATA DE CONTROLES Y LLAVES'!G$6:G1000},2,FALSE),"")} -> SEIJA | E88: ACTIVO
B89: 85a | C89: {=IFNA(VLOOKUP(B89,{'DATA DE CONTROLES Y LLAVES'!I$6:I1000,'DATA DE CONTROLES Y LLAVES'!F$6:F1000},2,FALSE),"")} -> CARLOS | D89: {=IFNA(VLOOKUP(B89,{'DATA DE CONTROLES Y LLAVES'!I$6:I1000,'DATA DE CONTROLES Y LLAVES'!G$6:G1000},2,FALSE),"")} -> GONZÁLEZ | E89: ACTIVO
B90: 86a | C90: {=IFNA(VLOOKUP(B90,{'DATA DE CONTROLES Y LLAVES'!I$6:I1000,'DATA DE CONTROLES Y LLAVES'!F$6:F1000},2,FALSE),"")} -> PABLO | D90: {=IFNA(VLOOKUP(B90,{'DATA DE CONTROLES Y LLAVES'!I$6:I1000,'DATA DE CONTROLES Y LLAVES'!G$6:G1000},2,FALSE),"")} -> GARMENDIA | E90: ACTIVO
B91: 87a | C91: {=IFNA(VLOOKUP(B91,{'DATA DE CONTROLES Y LLAVES'!I$6:I1000,'DATA DE CONTROLES Y LLAVES'!F$6:F1000},2,FALSE),"")} -> PEDRO | D91: {=IFNA(VLOOKUP(B91,{'DATA DE CONTROLES Y LLAVES'!I$6:I1000,'DATA DE CONTROLES Y LLAVES'!G$6:G1000},2,FALSE),"")} -> CARVAJAL | E91: ACTIVO
B92: 88a | C92: {=IFNA(VLOOKUP(B92,{'DATA DE CONTROLES Y LLAVES'!I$6:I1000,'DATA DE CONTROLES Y LLAVES'!F$6:F1000},2,FALSE),"")} -> RANIER | D92: {=IFNA(VLOOKUP(B92,{'DATA DE CONTROLES Y LLAVES'!I$6:I1000,'DATA DE CONTROLES Y LLAVES'!G$6:G1000},2,FALSE),"")} -> MALAVE | E92: BLOQUEADO
B93: 89a | C93: {=IFNA(VLOOKUP(B93,{'DATA DE CONTROLES Y LLAVES'!I$6:I1000,'DATA DE CONTROLES Y LLAVES'!F$6:F1000},2,FALSE),"")} -> ALOIS | D93: {=IFNA(VLOOKUP(B93,{'DATA DE CONTROLES Y LLAVES'!I$6:I1000,'DATA DE CONTROLES Y LLAVES'!G$6:G1000},2,FALSE),"")} -> QUIJANOS | E93: ACTIVO
B94: 90a | C94: {=IFNA(VLOOKUP(B94,{'DATA DE CONTROLES Y LLAVES'!I$6:I1000,'DATA DE CONTROLES Y LLAVES'!F$6:F1000},2,FALSE),"")} -> DARLING | D94: {=IFNA(VLOOKUP(B94,{'DATA DE CONTROLES Y LLAVES'!I$6:I1000,'DATA DE CONTROLES Y LLAVES'!G$6:G1000},2,FALSE),"")} -> VIVAS | E94: ACTIVO
B95: 91a | C95: {=IFNA(VLOOKUP(B95,{'DATA DE CONTROLES Y LLAVES'!I$6:I1000,'DATA DE CONTROLES Y LLAVES'!F$6:F1000},2,FALSE),"")} -> JOJANDUAR | D95: {=IFNA(VLOOKUP(B95,{'DATA DE CONTROLES Y LLAVES'!I$6:I1000,'DATA DE CONTROLES Y LLAVES'!G$6:G1000},2,FALSE),"")} -> QUIJANOS | E95: BLOQUEADO
B96: 92a | C96: {=IFNA(VLOOKUP(B96,{'DATA DE CONTROLES Y LLAVES'!I$6:I1000,'DATA DE CONTROLES Y LLAVES'!F$6:F1000},2,FALSE),"")} -> ALEJANDRO | D96: {=IFNA(VLOOKUP(B96,{'DATA DE CONTROLES Y LLAVES'!I$6:I1000,'DATA DE CONTROLES Y LLAVES'!G$6:G1000},2,FALSE),"")} -> VILLEGAS | E96: ACTIVO
B97: 93a | C97: {=IFNA(VLOOKUP(B97,{'DATA DE CONTROLES Y LLAVES'!I$6:I1000,'DATA DE CONTROLES Y LLAVES'!F$6:F1000},2,FALSE),"")} -> JETSER | D97: {=IFNA(VLOOKUP(B97,{'DATA DE CONTROLES Y LLAVES'!I$6:I1000,'DATA DE CONTROLES Y LLAVES'!G$6:G1000},2,FALSE),"")} -> DAZA | E97: BLOQUEADO
B98: 94a | C98: {=IFNA(VLOOKUP(B98,{'DATA DE CONTROLES Y LLAVES'!I$6:I1000,'DATA DE CONTROLES Y LLAVES'!F$6:F1000},2,FALSE),"")} -> CÉSAR | D98: {=IFNA(VLOOKUP(B98,{'DATA DE CONTROLES Y LLAVES'!I$6:I1000,'DATA DE CONTROLES Y LLAVES'!G$6:G1000},2,FALSE),"")} -> GONZÁLEZ | E98: BLOQUEADO
B99: 95a | C99: {=IFNA(VLOOKUP(B99,{'DATA DE CONTROLES Y LLAVES'!I$6:I1000,'DATA DE CONTROLES Y LLAVES'!F$6:F1000},2,FALSE),"")} | D99: {=IFNA(VLOOKUP(B99,{'DATA DE CONTROLES Y LLAVES'!I$6:I1000,'DATA DE CONTROLES Y LLAVES'!G$6:G1000},2,FALSE),"")} | E99: BLOQUEADO
B100: 96a | C100: {=IFNA(VLOOKUP(B100,{'DATA DE CONTROLES Y LLAVES'!I$6:I1000,'DATA DE CONTROLES Y LLAVES'!F$6:F1000},2,FALSE),"")} -> AMARILIS | D100: {=IFNA(VLOOKUP(B100,{'DATA DE CONTROLES Y LLAVES'!I$6:I1000,'DATA DE CONTROLES Y LLAVES'!G$6:G1000},2,FALSE),"")} -> GUTIÉRREZ | E100: ACTIVO
B101: 97a | C101: {=IFNA(VLOOKUP(B101,{'DATA DE CONTROLES Y LLAVES'!I$6:I1000,'DATA DE CONTROLES Y LLAVES'!F$6:F1000},2,FALSE),"")} -> FELICIA | D101: {=IFNA(VLOOKUP(B101,{'DATA DE CONTROLES Y LLAVES'!I$6:I1000,'DATA DE CONTROLES Y LLAVES'!G$6:G1000},2,FALSE),"")} -> LUGO | E101: BLOQUEADO
B102: 98a | C102: {=IFNA(VLOOKUP(B102,{'DATA DE CONTROLES Y LLAVES'!I$6:I1000,'DATA DE CONTROLES Y LLAVES'!F$6:F1000},2,FALSE),"")} -> IRIS | D102: {=IFNA(VLOOKUP(B102,{'DATA DE CONTROLES Y LLAVES'!I$6:I1000,'DATA DE CONTROLES Y LLAVES'!G$6:G1000},2,FALSE),"")} -> GASSETTE | E102: ACTIVO
...
